{
  "baseline": "legacy-handrolled-canvas",
  "current": {
    "A": "mod-07-annotations",
    "B": null
  },
  "tasks": [
    {
      "id": "mod-00-task-tracking",
      "module": "tracking",
      "title": "Task files and orchestration rules",
      "lane": "A",
      "status": "done",
      "depends_on": [],
      "writes": [
        "docs/tasks/canvas-xyflow-rewrite.md",
        "docs/tasks/canvas-xyflow-rewrite.json"
      ],
      "passes": [
        "paired markdown/json task files exist",
        "all later modules have dependencies and local pass gates"
      ]
    },
    {
      "id": "mod-01-scene-contracts",
      "module": "scene",
      "title": "Scene contracts and shared state boundary",
      "lane": "A",
      "status": "done",
      "depends_on": [
        "mod-00-task-tracking"
      ],
      "writes": [
        "src/types",
        "src/stores",
        "src/canvas"
      ],
      "passes": [
        "scene/runtime types compile",
        "legacy snapshot can map into new in-memory shape",
        "no renderer path switched yet"
      ]
    },
    {
      "id": "mod-02-persistence-bridge",
      "module": "persistence",
      "title": "Legacy snapshot read bridge",
      "lane": "B",
      "status": "done",
      "depends_on": [
        "mod-01-scene-contracts"
      ],
      "writes": [
        "src/snapshotState.ts",
        "src/App.tsx"
      ],
      "passes": [
        "legacy snapshot loads into new contracts",
        "no new renderer path is required for migration"
      ]
    },
    {
      "id": "mod-03-xyflow-shell",
      "module": "canvas",
      "title": "XyFlow shell, camera, and fallback switch",
      "lane": "A",
      "status": "done",
      "depends_on": [
        "mod-01-scene-contracts"
      ],
      "writes": [
        "src/canvas",
        "src/App.tsx"
      ],
      "passes": [
        "new shell mounts",
        "pan/zoom/fit works",
        "legacy shell remains switchable"
      ]
    },
    {
      "id": "mod-04-project-worktree-nodes",
      "module": "nodes",
      "title": "Project and worktree node projection",
      "lane": "A",
      "status": "done",
      "depends_on": [
        "mod-03-xyflow-shell"
      ],
      "writes": [
        "src/containers",
        "src/canvas",
        "src/stores/projectStore.ts"
      ],
      "passes": [
        "project/worktree nodes render in XyFlow",
        "drag path no longer depends on legacy overlap solving per frame"
      ]
    },
    {
      "id": "mod-05-terminal-runtime",
      "module": "terminal",
      "title": "Terminal runtime containment and LOD",
      "lane": "B",
      "status": "done",
      "depends_on": [
        "mod-01-scene-contracts"
      ],
      "writes": [
        "src/terminal",
        "src/containers/WorktreeContainer.tsx"
      ],
      "passes": [
        "focused terminal stays live",
        "visible non-focused terminals can degrade safely",
        "offscreen terminals do not keep full DOM cost"
      ]
    },
    {
      "id": "mod-06-interactions",
      "module": "interaction",
      "title": "Selection, focus, delete, and keyboard merge",
      "lane": "B",
      "status": "done",
      "depends_on": [
        "mod-04-project-worktree-nodes",
        "mod-05-terminal-runtime"
      ],
      "writes": [
        "src/hooks",
        "src/stores/selectionStore.ts",
        "src/utils"
      ],
      "passes": [
        "box select/delete/focus cycle/pan helpers work end to end",
        "selection sources are unified"
      ]
    },
    {
      "id": "mod-07-annotations",
      "module": "drawing",
      "title": "Internal annotation subsystem",
      "lane": "A",
      "status": "pending",
      "depends_on": [
        "mod-02-persistence-bridge",
        "mod-03-xyflow-shell"
      ],
      "writes": [
        "src/canvas",
        "src/stores/drawingStore.ts",
        "src/toolbar/DrawingPanel.tsx"
      ],
      "passes": [
        "draw/save/restore/delete works",
        "annotations stay aligned with viewport",
        "no second canvas library introduced"
      ]
    },
    {
      "id": "mod-08-cutover",
      "module": "cutover",
      "title": "Default-path switch and v2 write path",
      "lane": "B",
      "status": "pending",
      "depends_on": [
        "mod-02-persistence-bridge",
        "mod-06-interactions",
        "mod-07-annotations"
      ],
      "writes": [
        "src/App.tsx",
        "src/snapshotState.ts",
        "src/canvas"
      ],
      "passes": [
        "legacy workspaces open",
        "new snapshots save and reload consistently",
        "new canvas is default with hidden fallback"
      ]
    },
    {
      "id": "mod-09-performance-closure",
      "module": "performance",
      "title": "Render audit, selector tightening, and final closure",
      "lane": "A",
      "status": "pending",
      "depends_on": [
        "mod-08-cutover"
      ],
      "writes": [
        "src/utils",
        "src/terminal",
        "src/canvas",
        "src/stores"
      ],
      "passes": [
        "single-node drag updates only affected subtrees",
        "offscreen nodes do not dominate render cost",
        "terminal DOM cost is bounded by LOD policy"
      ]
    }
  ]
}
